{
  "metadata": {
    "generated_at": "2025-07-24T15:21:36.544030",
    "total_experiments": 3,
    "datasets": [
      "cifar10",
      "mnist"
    ],
    "model_types": [
      "mlp",
      "resnet",
      "simple_cnn"
    ],
    "strategies": [
      "pseudo_label",
      "traditional"
    ]
  },
  "summary": {
    "datasets": {
      "cifar10": {
        "best_accuracy": 89.3,
        "avg_accuracy": 85.69999999999999,
        "experiments": 2
      },
      "mnist": {
        "best_accuracy": 98.26,
        "avg_accuracy": 98.26,
        "experiments": 1
      }
    },
    "model_types": {
      "simple_cnn": {
        "best_accuracy": 82.1,
        "avg_accuracy": 82.1,
        "experiments": 1
      },
      "robust_cnn": {
        "best_accuracy": 0,
        "avg_accuracy": 0,
        "experiments": 0
      },
      "resnet": {
        "best_accuracy": 89.3,
        "avg_accuracy": 89.3,
        "experiments": 1
      },
      "robust_resnet": {
        "best_accuracy": 0,
        "avg_accuracy": 0,
        "experiments": 0
      },
      "mlp": {
        "best_accuracy": 98.26,
        "avg_accuracy": 98.26,
        "experiments": 1
      },
      "robust_mlp": {
        "best_accuracy": 0,
        "avg_accuracy": 0,
        "experiments": 0
      }
    },
    "strategies": {
      "traditional": {
        "best_accuracy": 89.3,
        "avg_accuracy": 0,
        "experiments": 2
      },
      "pseudo_label": {
        "best_accuracy": 98.26,
        "avg_accuracy": 0,
        "experiments": 1
      }
    },
    "overall": {
      "total_experiments": 3,
      "best_accuracy": 98.26,
      "avg_accuracy": 89.88666666666666,
      "std_accuracy": 6.610321895002967
    }
  },
  "comparison_table": [
    {
      "Dataset": "cifar10",
      "Model_Type": "simple_cnn",
      "Strategy": "traditional",
      "Accuracy": 82.1,
      "Training_Time_Min": 90,
      "Memory_Usage_GB": 2.3,
      "Experiment_Dir": "experiments/noise_robustness/noise_robustness_cifar10_simple_cnn_sample"
    },
    {
      "Dataset": "cifar10",
      "Model_Type": "resnet",
      "Strategy": "traditional",
      "Accuracy": 89.3,
      "Training_Time_Min": 450,
      "Memory_Usage_GB": 4.2,
      "Experiment_Dir": "experiments/noise_robustness/noise_robustness_cifar10_resnet_sample"
    },
    {
      "Dataset": "mnist",
      "Model_Type": "mlp",
      "Strategy": "pseudo_label",
      "Accuracy": 98.26,
      "Training_Time_Min": 42,
      "Memory_Usage_GB": 2.3,
      "Experiment_Dir": "experiments/semi_supervised/mnist_mlp_labeled0.1_sample"
    }
  ],
  "rankings": {
    "by_accuracy": [
      {
        "dataset": "mnist",
        "model_type": "mlp",
        "strategy": "pseudo_label",
        "accuracy": 98.26,
        "experiment_dir": "experiments/semi_supervised/mnist_mlp_labeled0.1_sample"
      },
      {
        "dataset": "cifar10",
        "model_type": "resnet",
        "strategy": "traditional",
        "accuracy": 89.3,
        "experiment_dir": "experiments/noise_robustness/noise_robustness_cifar10_resnet_sample"
      },
      {
        "dataset": "cifar10",
        "model_type": "simple_cnn",
        "strategy": "traditional",
        "accuracy": 82.1,
        "experiment_dir": "experiments/noise_robustness/noise_robustness_cifar10_simple_cnn_sample"
      }
    ],
    "by_dataset": {
      "cifar10": [
        {
          "dataset": "cifar10",
          "model_type": "resnet",
          "strategy": "traditional",
          "accuracy": 89.3,
          "experiment_dir": "experiments/noise_robustness/noise_robustness_cifar10_resnet_sample"
        },
        {
          "dataset": "cifar10",
          "model_type": "simple_cnn",
          "strategy": "traditional",
          "accuracy": 82.1,
          "experiment_dir": "experiments/noise_robustness/noise_robustness_cifar10_simple_cnn_sample"
        }
      ],
      "mnist": [
        {
          "dataset": "mnist",
          "model_type": "mlp",
          "strategy": "pseudo_label",
          "accuracy": 98.26,
          "experiment_dir": "experiments/semi_supervised/mnist_mlp_labeled0.1_sample"
        }
      ]
    },
    "by_model_type": {
      "mlp": [
        {
          "dataset": "mnist",
          "model_type": "mlp",
          "strategy": "pseudo_label",
          "accuracy": 98.26,
          "experiment_dir": "experiments/semi_supervised/mnist_mlp_labeled0.1_sample"
        }
      ],
      "resnet": [
        {
          "dataset": "cifar10",
          "model_type": "resnet",
          "strategy": "traditional",
          "accuracy": 89.3,
          "experiment_dir": "experiments/noise_robustness/noise_robustness_cifar10_resnet_sample"
        }
      ],
      "simple_cnn": [
        {
          "dataset": "cifar10",
          "model_type": "simple_cnn",
          "strategy": "traditional",
          "accuracy": 82.1,
          "experiment_dir": "experiments/noise_robustness/noise_robustness_cifar10_simple_cnn_sample"
        }
      ]
    },
    "by_strategy": {
      "pseudo_label": [
        {
          "dataset": "mnist",
          "model_type": "mlp",
          "strategy": "pseudo_label",
          "accuracy": 98.26,
          "experiment_dir": "experiments/semi_supervised/mnist_mlp_labeled0.1_sample"
        }
      ],
      "traditional": [
        {
          "dataset": "cifar10",
          "model_type": "resnet",
          "strategy": "traditional",
          "accuracy": 89.3,
          "experiment_dir": "experiments/noise_robustness/noise_robustness_cifar10_resnet_sample"
        },
        {
          "dataset": "cifar10",
          "model_type": "simple_cnn",
          "strategy": "traditional",
          "accuracy": 82.1,
          "experiment_dir": "experiments/noise_robustness/noise_robustness_cifar10_simple_cnn_sample"
        }
      ]
    }
  },
  "raw_results": {
    "cifar10": {
      "simple_cnn": {
        "traditional": {
          "config": {
            "dataset": "cifar10",
            "model_type": "simple_cnn",
            "strategy": "traditional",
            "epochs": 50,
            "batch_size": 128,
            "learning_rate": 0.001
          },
          "results": {
            "best_val_acc": 82.1,
            "final_test_acc": 82.1,
            "training_time": 90,
            "memory_usage": 2.3,
            "metrics": {
              "val_acc": [
                80.1,
                81.1,
                82.1
              ],
              "train_acc": [
                81.1,
                81.6,
                82.1
              ]
            }
          },
          "experiment_dir": "experiments/noise_robustness/noise_robustness_cifar10_simple_cnn_sample"
        }
      },
      "robust_cnn": {},
      "resnet": {
        "traditional": {
          "config": {
            "dataset": "cifar10",
            "model_type": "resnet",
            "strategy": "combined",
            "epochs": 50,
            "batch_size": 128,
            "learning_rate": 0.001
          },
          "results": {
            "best_val_acc": 89.3,
            "final_test_acc": 89.3,
            "training_time": 450,
            "memory_usage": 4.2,
            "metrics": {
              "val_acc": [
                87.3,
                88.3,
                89.3
              ],
              "train_acc": [
                88.3,
                88.8,
                89.3
              ]
            }
          },
          "experiment_dir": "experiments/noise_robustness/noise_robustness_cifar10_resnet_sample"
        }
      },
      "robust_resnet": {},
      "mlp": {},
      "robust_mlp": {}
    },
    "mnist": {
      "simple_cnn": {},
      "robust_cnn": {},
      "resnet": {},
      "robust_resnet": {},
      "mlp": {
        "pseudo_label": {
          "config": {
            "dataset": "mnist",
            "model_type": "mlp",
            "strategy": "pseudo_label",
            "epochs": 50,
            "batch_size": 128,
            "learning_rate": 0.001
          },
          "results": {
            "best_val_acc": 98.26,
            "final_test_acc": 98.26,
            "training_time": 42,
            "memory_usage": 2.3,
            "metrics": {
              "val_acc": [
                96.26,
                97.26,
                98.26
              ],
              "train_acc": [
                97.26,
                97.76,
                98.26
              ]
            }
          },
          "experiment_dir": "experiments/semi_supervised/mnist_mlp_labeled0.1_sample"
        }
      },
      "robust_mlp": {}
    }
  }
}